yeonjae_universal_notion_sync/__init__.py
yeonjae_universal_notion_sync/config.py
yeonjae_universal_notion_sync/models.py
yeonjae_universal_notion_sync/py.typed
yeonjae_universal_notion_sync/service.py
yeonjae_universal_notion_sync/tasks.py
yeonjae_universal_notion_sync-1.0.5.dist-info/METADATA
yeonjae_universal_notion_sync-1.0.5.dist-info/WHEEL
yeonjae_universal_notion_sync-1.0.5.dist-info/top_level.txt
yeonjae_universal_notion_sync-1.0.5.dist-info/RECORD
